callofduty/__init__.py
callofduty/auth.py
callofduty/client.py
callofduty/enums.py
callofduty/errors.py
callofduty/feed.py
callofduty/http.py
callofduty/leaderboard.py
callofduty/loadout.py
callofduty/loot.py
callofduty/match.py
callofduty/object.py
callofduty/player.py
callofduty/squad.py
callofduty/stamp.py
callofduty/utils.py
callofduty.py-1.4.0.dist-info/LICENSE
callofduty.py-1.4.0.dist-info/WHEEL
callofduty.py-1.4.0.dist-info/METADATA
callofduty.py-1.4.0.dist-info/RECORD
