Metadata-Version: 2.1
Name: callofduty.py
Version: 1.4.0
Summary: CallofDuty.py is an asynchronous, object-oriented Python wrapper for the Call of Duty API.
Home-page: https://github.com/EthanC/CallofDuty.py
License: MIT
Keywords: call-of-duty-py,callofduty,call-of-duty,cod,api
Author: EthanC
Author-email: EthanC@github.com
Requires-Python: >=3.10,<4.0
Classifier: Development Status :: 5 - Production/Stable
Classifier: Framework :: AsyncIO
Classifier: Intended Audience :: Developers
Classifier: License :: OSI Approved :: MIT License
Classifier: Natural Language :: English
Classifier: Operating System :: OS Independent
Classifier: Programming Language :: Python :: 3
Classifier: Programming Language :: Python :: 3.10
Classifier: Topic :: Games/Entertainment
Classifier: Topic :: Games/Entertainment :: First Person Shooters
Classifier: Topic :: Internet
Classifier: Topic :: Software Development :: Libraries
Classifier: Topic :: Software Development :: Libraries :: Python Modules
Classifier: Typing :: Typed
Requires-Dist: httpx (>=0.21.1,<0.22.0)
Project-URL: Changelog, https://github.com/EthanC/CallofDuty.py/releases
Project-URL: Discord, https://discord.gg/CallofDuty
Project-URL: Issue Tracker, https://github.com/EthanC/CallofDuty.py/issues
Project-URL: Repository, https://github.com/EthanC/CallofDuty.py
Project-URL: Twitter, https://twitter.com/Mxtive
